advvaex/__init__.py
advvaex/core.py
advvaex-0.1.0.dist-info/LICENSE
advvaex-0.1.0.dist-info/METADATA
advvaex-0.1.0.dist-info/WHEEL
advvaex-0.1.0.dist-info/top_level.txt
advvaex-0.1.0.dist-info/RECORD
